{
  "symbol": "BTC/USDT",
  "market": "crypto",
  "analyzed_at": "2026-06-25T21:31:04.721446+08:00",
  "current_price_range": "",
  "recent_performance": "",
  "sentiment_score": 42,
  "sentiment_label": "中性",
  "sentiment_summary": "📰关键词兜底: 130条标题 → 看跌36条/看涨24条 (Gemini: Gemini JSON解析失败: Expecting value: line 1 column 1 (char 0))",
  "key_drivers": [
    {
      "factor": "比特币亏损持仓量达到历史新高 1,083万 BTC - Moomoo",
      "impact": "negative",
      "strength": 3,
      "source": "headline_keyword"
    },
    {
      "factor": "比特币亏损持仓量达到历史新高 1,083万 BTC - Moomoo",
      "impact": "positive",
      "strength": 3,
      "source": "headline_keyword"
    },
    {
      "factor": "  → 比特币亏损持仓量达到历史新高 1,083万 BTC&nbsp;&nbsp;Moomoo",
      "impact": "negative",
      "strength": 3,
      "source": "headline_keyword"
    },
    {
      "factor": "  → 比特币亏损持仓量达到历史新高 1,083万 BTC&nbsp;&nbsp;Moomoo",
      "impact": "positive",
      "strength": 3,
      "source": "headline_keyword"
    },
    {
      "factor": "比特币亏损持仓量达到历史新高 1,083万 BTC - 富途牛牛",
      "impact": "negative",
      "strength": 3,
      "source": "headline_keyword"
    }
  ],
  "platform_sentiment": {},
  "risks": [
    "Gemini API不可用，使用关键词分析"
  ],
  "opportunities": [],
  "macro_cycle": {},
  "cycle_position": "",
  "cycle_confidence": 40,
  "sentiment_trend": "",
  "divergence_note": "",
  "conclusion": "",
  "trading_suggestion": "",
  "data_sources": [
    "google_news",
    "Google News Business",
    "Yahoo Finance",
    "CoinTelegraph",
    "CryptoSlate",
    "Decrypt",
    "律动BlockBeats",
    "CoinMarketCap"
  ],
  "data_count": 130,
  "model_used": "keyword_fallback",
  "cache_hit": false
}